eldar_fancy_text_matrix-0.1.0.dist-info/licenses/LICENSE
fancy_text/__init__.py
eldar_fancy_text_matrix-0.1.0.dist-info/METADATA
eldar_fancy_text_matrix-0.1.0.dist-info/WHEEL
eldar_fancy_text_matrix-0.1.0.dist-info/top_level.txt
eldar_fancy_text_matrix-0.1.0.dist-info/RECORD
