Metadata-Version: 2.4
Name: eldar-fancy-text-matrix
Version: 0.1.0
Summary: Emoji fancy text generator
Home-page: https://github.com/eldareliy/fancy_text
Author: Eldar Eliyev
Classifier: Programming Language :: Python :: 3
Classifier: License :: OSI Approved :: MIT License
Classifier: Operating System :: OS Independent
Requires-Python: >=3.10
License-File: LICENSE
Requires-Dist: colorama
Dynamic: author
Dynamic: classifier
Dynamic: description
Dynamic: description-content-type
Dynamic: home-page
Dynamic: license-file
Dynamic: requires-dist
Dynamic: requires-python
Dynamic: summary
